lark_ambig_tools.py
lark_ambig_tools-1.0.0.dist-info/LICENSE
lark_ambig_tools-1.0.0.dist-info/METADATA
lark_ambig_tools-1.0.0.dist-info/WHEEL
lark_ambig_tools-1.0.0.dist-info/top_level.txt
lark_ambig_tools-1.0.0.dist-info/RECORD
