Metadata-Version: 2.1
Name: lark-ambig-tools
Version: 1.0.0
Summary: Utilities for lark's ambiguous trees
Home-page: https://github.com/chanicpanic/lark-ambig-tools
Author: Chanic Panic
Author-email: dev@chanicpanic.com
License: MIT
Keywords: lark ambiguity earley tree
Platform: any
Classifier: Development Status :: 4 - Beta
Classifier: Environment :: Console
Classifier: Intended Audience :: Developers
Classifier: License :: OSI Approved :: MIT License
Classifier: Natural Language :: English
Classifier: Operating System :: OS Independent
Classifier: Programming Language :: Python :: 3
Classifier: Programming Language :: Python :: 3 :: Only
Classifier: Programming Language :: Python :: 3.6
Classifier: Programming Language :: Python :: 3.7
Classifier: Programming Language :: Python :: 3.8
Classifier: Programming Language :: Python :: 3.9
Classifier: Programming Language :: Python :: 3.10
Classifier: Programming Language :: Python :: Implementation :: CPython
Classifier: Topic :: Software Development :: Libraries :: Python Modules
Classifier: Topic :: Text Processing :: General
Classifier: Topic :: Text Processing :: Linguistic
Classifier: Topic :: Utilities
Classifier: Typing :: Typed
Requires-Python: >=3.6
License-File: LICENSE
Requires-Dist: lark
Provides-Extra: benchmark
Requires-Dist: pytest (~=7.0) ; extra == 'benchmark'
Requires-Dist: pytest-benchmark (~=3.0) ; extra == 'benchmark'
